README.md
setup.py
ap_perf/__init__.py
ap_perf/common_metrics.py
ap_perf/expression.py
ap_perf/layer.py
ap_perf/metric.py
ap_perf/projection.py
ap_perf.egg-info/PKG-INFO
ap_perf.egg-info/SOURCES.txt
ap_perf.egg-info/dependency_links.txt
ap_perf.egg-info/not-zip-safe
ap_perf.egg-info/requires.txt
ap_perf.egg-info/top_level.txt
test/test_metric.py