Metadata-Version: 1.0
Name: ap-perf
Version: 0.1.1
Summary: AP-Perf: Incorporating Generic Performance Metrics in Differentiable Learning
Home-page: http://github.com/rizalzaf/ap_perf
Author: Rizal Fathony
Author-email: rizal@fathony.com
License: MIT
Platform: UNKNOWN
